mypy_pure/__init__.py
mypy_pure/configuration.py
mypy_pure/decorators.py
mypy_pure/plugin.py
mypy_pure/py.typed
mypy_pure/purity/__init__.py
mypy_pure/purity/checker.py
mypy_pure/purity/types.py
mypy_pure/purity/visitor.py
mypy_pure/tests/__init__.py
mypy_pure/tests/test_decorators.py
mypy_pure/tests/test_plugin.py
mypy_pure/tests/resources/external_blacklisted_but_pure.py
mypy_pure/tests/resources/external_module.py
mypy_pure/tests/resources/external_module_dotted.py
mypy_pure/tests/resources/external_module_with_pure.py
mypy_pure/tests/resources/pure_async_function.py
mypy_pure/tests/resources/pure_calls_custom_impure.py
mypy_pure/tests/resources/pure_calls_external_impure.py
mypy_pure/tests/resources/pure_calls_impure_deeply_indirect.py
mypy_pure/tests/resources/pure_calls_impure_indirect.py
mypy_pure/tests/resources/pure_calls_impure_stdlib.py
mypy_pure/tests/resources/pure_calls_multiple_impure.py
mypy_pure/tests/resources/pure_calls_print.py
mypy_pure/tests/resources/pure_calls_pure.py
mypy_pure/tests/resources/pure_calls_sleep.py
mypy_pure/tests/resources/pure_class_method.py
mypy_pure/tests/resources/pure_decorators_module.py
mypy_pure/tests/resources/pure_import_alias.py
mypy_pure/tests/resources/pure_instance_method.py
mypy_pure/tests/resources/pure_is_ok.py
mypy_pure/tests/resources/pure_mutually_recursive.py
mypy_pure/tests/resources/pure_nested_function.py
mypy_pure/tests/resources/pure_property_method.py
mypy_pure/tests/resources/pure_recursive.py
mypy_pure/tests/resources/pure_relative_import.py
mypy_pure/tests/resources/pure_static_method.py
mypy_pure/tests/resources/pure_uses_blacklisted_external.py
mypy_pure/tests/resources/pure_uses_custom_pure.py
mypy_pure/tests/resources/pure_uses_dotted_names.py
mypy_pure/tests/resources/pure_whitelist_priority.py
mypy_pure/tests/resources/pure_whitelisted_callee.py
mypy_pure-0.2.2.dist-info/licenses/LICENSE
mypy_pure-0.2.2.dist-info/METADATA
mypy_pure-0.2.2.dist-info/WHEEL
mypy_pure-0.2.2.dist-info/entry_points.txt
mypy_pure-0.2.2.dist-info/top_level.txt
mypy_pure-0.2.2.dist-info/RECORD
