Metadata-Version: 2.4
Name: mypy-pure
Version: 0.2.2
Summary: A mypy plugin that adds support for checking pure functions.
Author-email: "Diego J. Romero López" <diegojromerolopez@gmail.com>
License: MIT
Project-URL: repository, https://github.com/diegojromerolopez/mypy-pure
Project-URL: documentation, https://github.com/diegojromerolopez/mypy-pure
Project-URL: Bug Tracker, https://github.com/diegojromerolopez/mypy-pure/issues
Classifier: Programming Language :: Python :: Implementation :: CPython
Classifier: Programming Language :: Python :: 3.10
Classifier: Programming Language :: Python :: 3.11
Classifier: Programming Language :: Python :: 3.12
Classifier: Programming Language :: Python :: 3.13
Classifier: Programming Language :: Python :: 3.14
Classifier: Topic :: Software Development :: Libraries
Classifier: Development Status :: 3 - Alpha
Classifier: License :: OSI Approved :: MIT License
Requires-Python: >=3.10
License-File: LICENSE
Requires-Dist: mypy>=1.0
Dynamic: license-file
